tap_zenloop/__init__.py
tap_zenloop/schemas/answers.json
tap_zenloop-0.1.2.dist-info/LICENSE
tap_zenloop-0.1.2.dist-info/METADATA
tap_zenloop-0.1.2.dist-info/WHEEL
tap_zenloop-0.1.2.dist-info/entry_points.txt
tap_zenloop-0.1.2.dist-info/top_level.txt
tap_zenloop-0.1.2.dist-info/RECORD
