Metadata-Version: 2.1
Name: tap-zenloop
Version: 0.1.2
Summary: Singer tap to extract Zenloop data
Home-page: https://cargo.one
Author: cargo.one
Classifier: Programming Language :: Python :: 3 :: Only
License-File: LICENSE
Requires-Dist: singer-python (==5.13.*)
Requires-Dist: requests (>=2.27.0)
Requires-Dist: pendulum (==2.1.*)
